pairLiftOver/__init__.py
pairLiftOver/chainfile.py
pairLiftOver/io.py
pairLiftOver/liftover.py
pairLiftOver/utilities.py
pairLiftOver/data/juicer_tools_1.11.09_jcuda.0.8.jar
pairLiftOver-0.2.1.data/scripts/pairLiftOver
pairLiftOver-0.2.1.dist-info/LICENSE
pairLiftOver-0.2.1.dist-info/METADATA
pairLiftOver-0.2.1.dist-info/WHEEL
pairLiftOver-0.2.1.dist-info/top_level.txt
pairLiftOver-0.2.1.dist-info/RECORD
